{
  "keywords": [
    {
      "concept": "虚拟电厂",
      "synonyms": ["VPP", "聚合商", "负荷聚合", "调度平台", "需求响应"],
      "stage": "商业模式"
    },
    {
      "concept": "储能",
      "synonyms": ["储能系统", "ESS", "电池储能", "工商业储能", "户用储能", "储能集成"],
      "stage": "战略梳理"
    },
    {
      "concept": "光伏",
      "synonyms": ["光伏系统", "PV", "太阳能", "户用光伏", "分布式光伏", "光伏发电"],
      "stage": "战略梳理"
    },
    {
      "concept": "设备商",
      "synonyms": ["设备制造商", "硬件厂商", "设备供应商", "生产厂商"],
      "stage": "商业模式"
    },
    {
      "concept": "集成商",
      "synonyms": ["系统集成商", "解决方案提供商", "EPC", "工程承包商"],
      "stage": "商业模式"
    },
    {
      "concept": "运营商",
      "synonyms": ["运营服务商", "服务提供商", "运维商", "资产管理"],
      "stage": "商业模式"
    },
    {
      "concept": "产品线",
      "synonyms": ["业务线", "产品组合", "业务板块", "产品矩阵"],
      "stage": "战略梳理"
    },
    {
      "concept": "客户群体",
      "synonyms": ["目标客户", "客户类型", "服务对象", "付费方", "终端用户"],
      "stage": "战略梳理"
    },
    {
      "concept": "收入结构",
      "synonyms": ["收入来源", "营收构成", "收入模式", "盈利来源"],
      "stage": "战略梳理"
    },
    {
      "concept": "毛利结构",
      "synonyms": ["毛利率", "利润构成", "盈利能力", "毛利分布"],
      "stage": "战略梳理"
    },
    {
      "concept": "交付情况",
      "synonyms": ["交付模式", "交付能力", "交付周期", "标准化程度"],
      "stage": "战略梳理"
    },
    {
      "concept": "资源分布",
      "synonyms": ["资源配置", "团队规模", "资金分布", "渠道资源"],
      "stage": "战略梳理"
    },
    {
      "concept": "战略目标",
      "synonyms": ["发展目标", "长期规划", "战略方向", "三年目标"],
      "stage": "战略梳理"
    },
    {
      "concept": "商业模式",
      "synonyms": ["盈利模式", "业务模式", "经营模式", "变现方式"],
      "stage": "商业模式"
    },
    {
      "concept": "诊断进度",
      "synonyms": ["诊断完成度", "诊断阶段", "诊断状态"],
      "stage": "战略梳理"
    },
    {
      "concept": "共识链",
      "synonyms": ["共识记录", "已确认事实", "诊断共识"],
      "stage": "战略梳理"
    },
    {
      "concept": "候选方案",
      "synonyms": ["候选", "方案建议", "初步建议", "方向建议"],
      "stage": "商业模式"
    },
    {
      "concept": "SKU",
      "synonyms": ["案例库", "知识卡片", "标杆案例", "行业案例"],
      "stage": "战略梳理"
    },
    {
      "concept": "微电网",
      "synonyms": ["微网", "分布式电网", "局域电网"],
      "stage": "商业模式"
    },
    {
      "concept": "重卡换电",
      "synonyms": ["换电站", "重卡电动化", "换电模式", "商用车换电"],
      "stage": "商业模式"
    },
    {
      "concept": "EPC工程",
      "synonyms": ["EPC", "工程总承包", "设计施工", "交钥匙工程"],
      "stage": "商业模式"
    },
    {
      "concept": "运维服务",
      "synonyms": ["运维", "运营维护", "售后服务", "长期运维"],
      "stage": "商业模式"
    },
    {
      "concept": "设备销售",
      "synonyms": ["硬件销售", "产品销售", "设备出货", "卖设备"],
      "stage": "商业模式"
    },
    {
      "concept": "运营服务",
      "synonyms": ["运营", "服务运营", "托管运营", "代运营"],
      "stage": "商业模式"
    },
    {
      "concept": "新能源",
      "synonyms": ["清洁能源", "绿色能源", "可再生能源", "低碳能源"],
      "stage": "战略梳理"
    },
    {
      "concept": "投资方",
      "synonyms": ["投资人", "投资机构", "资方", "财务投资"],
      "stage": "商业模式"
    },
    {
      "concept": "终端用户",
      "synonyms": ["终端", "最终用户", "C端用户", "B端用户"],
      "stage": "战略梳理"
    },
    {
      "concept": "增长",
      "synonyms": ["业务增长", "营收增长", "规模扩张", "增长驱动"],
      "stage": "战略梳理"
    },
    {
      "concept": "盈利",
      "synonyms": ["利润", "赚钱", "盈利能力", "盈利点"],
      "stage": "战略梳理"
    },
    {
      "concept": "方向",
      "synonyms": ["战略方向", "发展方向", "业务方向", "转型方向"],
      "stage": "战略梳理"
    },
    {
      "concept": "聚焦",
      "synonyms": ["聚焦战略", "专注", "聚焦主业", "收缩战线"],
      "stage": "战略梳理"
    },
    {
      "concept": "多元",
      "synonyms": ["多元化", "多业务", "业务多元", "扩张"],
      "stage": "战略梳理"
    },
    {
      "concept": "重资产",
      "synonyms": ["资产密集", "重投入", "重资产模式", "资产型"],
      "stage": "商业模式"
    },
    {
      "concept": "轻资产",
      "synonyms": ["轻资产模式", "轻投入", "服务型", "平台型"],
      "stage": "商业模式"
    },
    {
      "concept": "自建",
      "synonyms": ["自建产能", "自主建设", "自建团队", "内部建设"],
      "stage": "商业模式"
    },
    {
      "concept": "合作",
      "synonyms": ["战略合作", "合作伙伴", "合作模式", "联合"],
      "stage": "商业模式"
    },
    {
      "concept": "稳健",
      "synonyms": ["稳健策略", "保守", "低风险", "稳健型"],
      "stage": "商业模式"
    },
    {
      "concept": "激进",
      "synonyms": ["激进策略", "激进型", "高风险", "快速扩张"],
      "stage": "商业模式"
    },
    {
      "concept": "风险偏好",
      "synonyms": ["风险承受", "风险态度", "风险容忍", "风险倾向"],
      "stage": "商业模式"
    },
    {
      "concept": "资源约束",
      "synonyms": ["资源限制", "资源瓶颈", "能力边界", "资源不足"],
      "stage": "战略梳理"
    },
    {
      "concept": "知识库",
      "synonyms": ["案例库", "知识沉淀", "行业洞察", "经验库"],
      "stage": "战略梳理"
    },
    {
      "concept": "作战卡",
      "synonyms": ["会前准备", "作战准备", "会议卡", "准备卡"],
      "stage": "战略梳理"
    },
    {
      "concept": "备忘录",
      "synonyms": ["会议纪要", "诊断报告", "会议总结", "会后文档"],
      "stage": "战略梳理"
    },
    {
      "concept": "飞书",
      "synonyms": ["多维表格", "飞书表格", "客户共识层", "Lark"],
      "stage": "战略梳理"
    },
    {
      "concept": "演示模式",
      "synonyms": ["Demo模式", "展示模式", "客户展示", "投屏模式"],
      "stage": "战略梳理"
    },
    {
      "concept": "工作模式",
      "synonyms": ["调试模式", "开发模式", "内部模式", "顾问模式"],
      "stage": "战略梳理"
    },
    {
      "concept": "追问建议",
      "synonyms": ["追问", "下一步问题", "建议问题", "追问卡"],
      "stage": "战略梳理"
    },
    {
      "concept": "备弹区",
      "synonyms": ["备弹", "SKU缓存", "侧边栏", "弹药库"],
      "stage": "战略梳理"
    },
    {
      "concept": "完整度",
      "synonyms": ["诊断完整度", "字段完整度", "信息完整度", "进度"],
      "stage": "战略梳理"
    }
  ]
}