{
  "roots": [
    {
      "name": "电力市场",
      "children": [
        {
          "name": "报价模式",
          "children": []
        },
        {
          "name": "结算机制",
          "children": []
        },
        {
          "name": "调度机制",
          "children": []
        },
        {
          "name": "聚合模式",
          "children": [
            {
              "name": "虚拟电厂",
              "children": [
                {
                  "name": "电网系虚拟电厂",
                  "children": []
                },
                {
                  "name": "售电型虚拟电厂",
                  "children": []
                },
                {
                  "name": "发电类型虚拟电厂",
                  "children": []
                },
                {
                  "name": "按聚合类型",
                  "children": [
                    {
                      "name": "电源型虚拟电厂",
                      "children": []
                    },
                    {
                      "name": "负荷型虚拟电厂",
                      "children": []
                    }
                  ]
                },
                {
                  "name": "按规模",
                  "children": [
                    {
                      "name": "城市级虚拟电厂",
                      "children": []
                    },
                    {
                      "name": "县级虚拟电厂",
                      "children": []
                    }
                  ]
                }
              ]
            }
          ]
        },
        {
          "name": "新能源基地",
          "children": []
        },
        {
          "name": "发电类型",
          "children": []
        },
        {
          "name": "电力传输",
          "children": []
        },
        {
          "name": "非正规市场",
          "children": []
        },
        {
          "name": "购电协议",
          "children": []
        },
        {
          "name": "辅助服务市场",
          "children": [
            {
              "name": "一次调频",
              "children": []
            },
            {
              "name": "二次调频",
              "children": []
            }
          ]
        }
      ]
    },
    {
      "name": "电力市场政策",
      "children": [
        {
          "name": "改革文件",
          "children": []
        },
        {
          "name": "政策原则",
          "children": []
        },
        {
          "name": "电价政策",
          "children": []
        }
      ]
    },
    {
      "name": "经济学概念",
      "children": [
        {
          "name": "市场失灵",
          "children": []
        },
        {
          "name": "反垄断",
          "children": []
        },
        {
          "name": "市场力约束",
          "children": []
        }
      ]
    },
    {
      "name": "企业运营",
      "children": [
        {
          "name": "资产组合管理",
          "children": []
        },
        {
          "name": "交易策略",
          "children": []
        },
        {
          "name": "内部结算",
          "children": []
        },
        {
          "name": "风险控制",
          "children": []
        },
        {
          "name": "EPC总承包",
          "children": []
        },
        {
          "name": "地方平台公司",
          "children": []
        },
        {
          "name": "综合能源服务",
          "children": []
        },
        {
          "name": "商业模式",
          "children": []
        }
      ]
    },
    {
      "name": "技术架构",
      "children": [
        {
          "name": "储能系统",
          "children": [
            {
              "name": "飞轮储能",
              "children": []
            }
          ]
        },
        {
          "name": "新能源设备",
          "children": [
            {
              "name": "换电设施",
              "children": []
            }
          ]
        },
        {
          "name": "智能硬件",
          "children": []
        },
        {
          "name": "新能源车辆",
          "children": []
        },
        {
          "name": "微电网",
          "children": [
            {
              "name": "矿山微电网",
              "children": []
            },
            {
              "name": "按连接方式",
              "children": [
                {
                  "name": "离网型微电网",
                  "children": []
                },
                {
                  "name": "并网型微电网",
                  "children": []
                }
              ]
            },
            {
              "name": "按电流类型",
              "children": [
                {
                  "name": "交直流混合微电网",
                  "children": []
                }
              ]
            },
            {
              "name": "按技术特点",
              "children": [
                {
                  "name": "光储直柔微电网",
                  "children": []
                }
              ]
            }
          ]
        },
        {
          "name": "能源管理系统",
          "children": []
        },
        {
          "name": "节能技术",
          "children": []
        }
      ]
    },
    {
      "name": "职业",
      "children": []
    },
    {
      "name": "海外市场",
      "children": []
    }
  ]
}