{"max_rounds": 5, "event": "Starting spec chatbot", "logger": "skus2ontology.chatbot", "level": "info", "timestamp": "2026-04-30T12:49:34.241964Z"}
{"entries": 958, "event": "Built name_to_path lookup", "logger": "skus2ontology.chatbot", "level": "info", "timestamp": "2026-04-30T12:49:34.246502Z"}
{"total_lines": 2, "matched": 0, "event": "slug\u2192path inline resolution", "logger": "skus2ontology.chatbot", "level": "info", "timestamp": "2026-04-30T12:49:34.246502Z"}
{"original_chars": 57, "compressed_chars": 12, "event": "Loaded mapping.md (compressed)", "logger": "skus2ontology.chatbot", "level": "info", "timestamp": "2026-04-30T12:49:34.247501Z"}
{"chars": 42, "event": "Loaded eureka.md", "logger": "skus2ontology.chatbot", "level": "info", "timestamp": "2026-04-30T12:49:34.247501Z"}
{"original_chars": 65604, "limit": 50000, "event": "SKU index summary truncated", "logger": "skus2ontology.chatbot", "level": "warning", "timestamp": "2026-04-30T12:59:27.031825Z"}
{"chars": 50033, "sku_count": 962, "event": "Built SKU index summary", "logger": "skus2ontology.chatbot", "level": "info", "timestamp": "2026-04-30T12:59:27.031825Z"}
{"draft_chars": 2998, "final_chars": 2998, "event": "Phase 2 anchor replacement complete", "logger": "skus2ontology.chatbot", "level": "info", "timestamp": "2026-04-30T13:00:32.659579Z"}
{"before": 11, "after": 11, "unwrapped": 0, "event": "unwrap_resolved_anchors", "logger": "skus2ontology.chatbot", "level": "info", "timestamp": "2026-04-30T13:00:32.660583Z"}
{"count": 11, "sample": ["\u3010\u951a\u70b9\uff1a\u5168\u5468\u671f\u65b9\u6848\u9636\u6bb5\u5212\u5206\u4e0e\u89e6\u53d1\u89c4\u5219\u3011", "\u3010\u951a\u70b9\uff1a\u5546\u4e1a\u6a21\u5f0f/\u76c8\u5229\u6a21\u578b\u53c2\u6570\u81ea\u5b9a\u4e49\u914d\u7f6e\u89c4\u5219\u3011", "\u3010\u951a\u70b9\uff1a15\u7c7b\u6210\u719f\u5546\u4e1a\u6a21\u5f0f\u89c4\u5219\u5e93\u3011", "\u3010\u951a\u70b9\uff1a21\u7c7b\u53ef\u590d\u7528\u76c8\u5229\u6a21\u578b\u7ec4\u4ef6\u5e93\u3011", "\u3010\u951a\u70b9\uff1a\u5404\u884c\u4e1a/\u5404\u9636\u6bb5\u843d\u5730\u6267\u884cSOP\u6a21\u677f\u5e93\u3011", "\u3010\u951a\u70b9\uff1a\u54a8\u8be2\u65b9\u6848\u843d\u5730\u98ce\u9669\u8282\u70b9\u4e0e\u89c4\u907f\u89c4\u5219\u5e93\u3011", "\u3010\u951a\u70b9\uff1a\u5404\u4e0a\u5e02\u677f\u4e0a\u5e02\u6210\u672c\u6d4b\u7b97\u89c4\u5219\u5e93\u3011", "\u3010\u951a\u70b9\uff1a\u4f01\u4e1a\u7ecf\u8425\u76d1\u7ba1\u5408\u89c4\u77e5\u8bc6\u5e93\u3011", "\u3010\u951a\u70b9\uff1a\u5408\u89c4\u98ce\u9669\u81ea\u52a8\u8bc6\u522b\u7b97\u6cd5\u3011", "\u3010\u951a\u70b9\uff1a\u5404\u884c\u4e1a\u5355\u5e97\u76c8\u5229\u6d4b\u7b97\u6a21\u578b\u3011"], "event": "Remaining anchors", "logger": "skus2ontology.chatbot", "level": "info", "timestamp": "2026-04-30T13:00:32.663749Z"}
{"backup": "G:\\Program Files\\AI coding\\\u77e5\u8bc6\u8403\u53d6\\\u5546\u4e1a\u6a21\u5f0f\u8d44\u672c\\\u8f93\u51fa\\ontology\\spec.md.bak.20260430_210032", "event": "Backed up existing spec.md", "logger": "skus2ontology.chatbot", "level": "info", "timestamp": "2026-04-30T13:00:32.665762Z"}
{"path": "G:\\Program Files\\AI coding\\\u77e5\u8bc6\u8403\u53d6\\\u5546\u4e1a\u6a21\u5f0f\u8d44\u672c\\\u8f93\u51fa\\ontology\\spec.md", "chars": 2998, "event": "Saved spec.md", "logger": "skus2ontology.chatbot", "level": "info", "timestamp": "2026-04-30T13:00:32.667931Z"}
{"check": "extra_chunk_bracket", "status": "PASS", "count": 0, "samples": [], "event": "spec_check", "logger": "skus2ontology.spec_validator", "level": "info", "timestamp": "2026-04-30T13:00:32.667931Z"}
{"check": "anchor_wrapping_chunk", "status": "PASS", "count": 0, "samples": [], "event": "spec_check", "logger": "skus2ontology.spec_validator", "level": "info", "timestamp": "2026-04-30T13:00:32.669285Z"}
{"check": "anchor_wrapping_sku", "status": "PASS", "count": 0, "samples": [], "event": "spec_check", "logger": "skus2ontology.spec_validator", "level": "info", "timestamp": "2026-04-30T13:00:32.669285Z"}
{"check": "sku_sku_concat", "status": "PASS", "count": 0, "samples": [], "event": "spec_check", "logger": "skus2ontology.spec_validator", "level": "info", "timestamp": "2026-04-30T13:00:32.669285Z"}
{"check": "sku_chunk_concat", "status": "PASS", "count": 0, "samples": [], "event": "spec_check", "logger": "skus2ontology.spec_validator", "level": "info", "timestamp": "2026-04-30T13:00:32.670535Z"}
{"check": "chunk_sku_concat", "status": "PASS", "count": 0, "samples": [], "event": "spec_check", "logger": "skus2ontology.spec_validator", "level": "info", "timestamp": "2026-04-30T13:00:32.670535Z"}
{"check": "sku_space_concat", "status": "PASS", "count": 0, "samples": [], "event": "spec_check", "logger": "skus2ontology.spec_validator", "level": "info", "timestamp": "2026-04-30T13:00:32.670535Z"}
{"check": "sku_range", "status": "PASS", "count": 0, "samples": [], "event": "spec_check", "logger": "skus2ontology.spec_validator", "level": "info", "timestamp": "2026-04-30T13:00:32.671727Z"}
{"check": "chinese_chunk_bracket", "status": "PASS", "count": 0, "samples": [], "event": "spec_check", "logger": "skus2ontology.spec_validator", "level": "info", "timestamp": "2026-04-30T13:00:32.671727Z"}
{"check": "chinese_sku_bracket", "status": "PASS", "count": 0, "samples": [], "event": "spec_check", "logger": "skus2ontology.spec_validator", "level": "info", "timestamp": "2026-04-30T13:00:32.671727Z"}
{"check": "remaining_anchor", "status": "INFO", "count": 11, "samples": ["\u3010\u951a\u70b9\uff1a\u5168\u5468\u671f\u65b9\u6848\u9636\u6bb5\u5212\u5206\u4e0e\u89e6\u53d1\u89c4\u5219\u3011", "\u3010\u951a\u70b9\uff1a\u5546\u4e1a\u6a21\u5f0f/\u76c8\u5229\u6a21\u578b\u53c2\u6570\u81ea\u5b9a\u4e49\u914d\u7f6e\u89c4\u5219\u3011", "\u3010\u951a\u70b9\uff1a15\u7c7b\u6210\u719f\u5546\u4e1a\u6a21\u5f0f\u89c4\u5219\u5e93\u3011"], "event": "spec_check", "logger": "skus2ontology.spec_validator", "level": "info", "timestamp": "2026-04-30T13:00:32.671727Z"}
{"sku_refs": 2, "sku_unique": 2, "chunk_refs": 3, "chunk_unique": 3, "event": "spec_stats", "logger": "skus2ontology.spec_validator", "level": "info", "timestamp": "2026-04-30T13:00:32.672833Z"}
{"event": "spec_validator PASSED", "logger": "skus2ontology.spec_validator", "level": "info", "timestamp": "2026-04-30T13:00:32.672833Z"}
{"path": "..\\\u5546\u4e1a\u6a21\u5f0f\u8d44\u672c\\\u8f93\u51fa\\ontology\\chat_log.json", "rounds": 5, "confirmed": false, "event": "Saved chat log", "logger": "skus2ontology.pipeline", "level": "info", "timestamp": "2026-04-30T13:00:32.704933Z"}
